{
	"schemaVersion": 1,
	"id": "sos",
	"version": "${version}",
	"name": "Sweets o' Spirits",
	"description": "Sweets o' thy Spirits",
	"authors": [
		"LordBee @Beelabs"
	],
	"contact": {
		"homepage": "https://fabricmc.net/",
		"sources": "https://github.com/FabricMC/fabric-example-mod"
	},
	"license": "MIT",
	"icon": "assets/sos/icon.png",
	"environment": "*",
	"entrypoints": {
		"main": [
			"net.beelabs.sos.common.SweetsOSpirits"
		],
		"fabric-datagen": [
			"net.beelabs.sos.data.SweetsOSpiritsDataGenerator"
		],
		"client": [
			"net.beelabs.sos.client.SweetsOSpiritsClient"
		]
	},
	"mixins": [
		"sos.mixins.json"
	],
	"depends": {
		"fabricloader": ">=0.16.9",
		"minecraft": "~1.20",
		"java": ">=17",
		"fabric-api": "*"
	},
	"suggests": {
		"another-mod": "*"
	}
}